{
  "meetName": "Kenner Summer Invitational",
  "events": [
    {
      "id": 1,
      "eventNumber": 1,
      "name": "Girls 6 & Under 25m Freestyle",
      "time": "9:00 AM",
      "heats": [
        { "heatNumber": 1, "lanes": [
            { "lane": 3, "swimmerName": "Riley Thibodeaux", "team": "KLR", "seedTime": "28.50" },
            { "lane": 4, "swimmerName": "Clara Boudreaux", "team": "AQN", "seedTime": "27.80" },
            { "lane": 5, "swimmerName": "Zoe Hebert", "team": "SCS", "seedTime": "28.15" }
        ]}
      ]
    },
    {
      "id": 2,
      "eventNumber": 2,
      "name": "Boys 6 & Under 25m Freestyle",
      "time": "9:02 AM",
      "heats": [
        { "heatNumber": 1, "lanes": [
            { "lane": 4, "swimmerName": "Leo Fontenot", "team": "BARR", "seedTime": "29.10" }
        ]}
      ]
    },
    {
      "id": 3,
      "eventNumber": 3,
      "name": "Girls 6 & Under 25m Backstroke",
      "time": "9:04 AM",
      "heats": [
        { "heatNumber": 1, "lanes": [
            { "lane": 4, "swimmerName": "Clara Boudreaux", "team": "AQN", "seedTime": "32.50" }
        ]}
      ]
    },
    {
      "id": 4,
      "eventNumber": 4,
      "name": "Boys 6 & Under 25m Backstroke",
      "time": "9:06 AM",
      "heats": [
        { "heatNumber": 1, "lanes": [
            { "lane": 4, "swimmerName": "Leo Fontenot", "team": "BARR", "seedTime": "34.00" }
        ]}
      ]
    },
    {
      "id": 5,
      "eventNumber": 5,
      "name": "Girls 7-8 25m Freestyle",
      "time": "9:08 AM",
      "heats": [
        { "heatNumber": 1, "lanes": [
            { "lane": 2, "swimmerName": "Sophia Leblanc", "team": "AQN", "seedTime": "19.85" },
            { "lane": 3, "swimmerName": "Ava Chen", "team": "SCS", "seedTime": "19.52" },
            { "lane": 4, "swimmerName": "Mia Broussard", "team": "KLR", "seedTime": "19.21" },
            { "lane": 5, "swimmerName": "Charlotte Jones", "team": "BARR", "seedTime": "19.48" },
            { "lane": 6, "swimmerName": "Isabella Nguyen", "team": "AQN", "seedTime": "19.77" }
        ]}
      ]
    },
    {
      "id": 6,
      "eventNumber": 6,
      "name": "Boys 7-8 25m Freestyle",
      "time": "9:10 AM",
      "heats": [
        { "heatNumber": 1, "lanes": [
            { "lane": 4, "swimmerName": "Liam Smith", "team": "AQN", "seedTime": "18.99" },
            { "lane": 5, "swimmerName": "Noah Johnson", "team": "SCS", "seedTime": "19.10" }
        ]}
      ]
    },
    {
        "id": 7,
        "eventNumber": 7,
        "name": "Girls 7-8 50m Freestyle",
        "time": "9:12 AM",
        "heats": [
            { "heatNumber": 1, "lanes": [
                { "lane": 4, "swimmerName": "Mia Broussard", "team": "KLR", "seedTime": "42.10" }
            ]}
        ]
    },
    {
        "id": 8,
        "eventNumber": 8,
        "name": "Boys 7-8 50m Freestyle",
        "time": "9:14 AM",
        "heats": [
            { "heatNumber": 1, "lanes": [
                { "lane": 4, "swimmerName": "Liam Smith", "team": "AQN", "seedTime": "41.50" }
            ]}
        ]
    },
    {
        "id": 9,
        "eventNumber": 9,
        "name": "Girls 7-8 25m Backstroke",
        "time": "9:16 AM",
        "heats": [
            { "heatNumber": 1, "lanes": [
                { "lane": 4, "swimmerName": "Ava Chen", "team": "SCS", "seedTime": "22.30" }
            ]}
        ]
    },
    {
        "id": 10,
        "eventNumber": 10,
        "name": "Boys 7-8 25m Backstroke",
        "time": "9:18 AM",
        "heats": [
            { "heatNumber": 1, "lanes": [
                { "lane": 4, "swimmerName": "Noah Johnson", "team": "SCS", "seedTime": "23.00" }
            ]}
        ]
    },
    {
        "id": 11,
        "eventNumber": 11,
        "name": "Girls 7-8 25m Breaststroke",
        "time": "9:20 AM",
        "heats": [
            { "heatNumber": 1, "lanes": [
                { "lane": 4, "swimmerName": "Sophia Leblanc", "team": "AQN", "seedTime": "25.10" }
            ]}
        ]
    },
    {
        "id": 12,
        "eventNumber": 12,
        "name": "Boys 7-8 25m Breaststroke",
        "time": "9:22 AM",
        "heats": [
            { "heatNumber": 1, "lanes": [
                { "lane": 4, "swimmerName": "Henry Martin", "team": "KLR", "seedTime": "26.30" }
            ]}
        ]
    },
    {
        "id": 13,
        "eventNumber": 13,
        "name": "Girls 7-8 25m Butterfly",
        "time": "9:24 AM",
        "heats": [
            { "heatNumber": 1, "lanes": [
                { "lane": 4, "swimmerName": "Charlotte Jones", "team": "BARR", "seedTime": "24.80" }
            ]}
        ]
    },
    {
        "id": 14,
        "eventNumber": 14,
        "name": "Boys 7-8 25m Butterfly",
        "time": "9:26 AM",
        "heats": [
            { "heatNumber": 1, "lanes": [
                { "lane": 4, "swimmerName": "Owen Dubois", "team": "AQN", "seedTime": "25.10" }
            ]}
        ]
    },
    {
        "id": 15,
        "eventNumber": 15,
        "name": "Girls 9-10 50m Freestyle",
        "time": "9:28 AM",
        "heats": [
            { "heatNumber": 1, "lanes": [
                { "lane": 2, "swimmerName": "Olivia Williams", "team": "KLR", "seedTime": "34.50" },
                { "lane": 3, "swimmerName": "Emma Brown", "team": "BARR", "seedTime": "33.80" },
                { "lane": 4, "swimmerName": "Amelia Miller", "team": "AQN", "seedTime": "33.20" },
                { "lane": 5, "swimmerName": "Evelyn Wilson", "team": "SCS", "seedTime": "33.75" }
            ]}
        ]
    },
    {
        "id": 16,
        "eventNumber": 16,
        "name": "Boys 9-10 50m Freestyle",
        "time": "9:30 AM",
        "heats": [
            { "heatNumber": 1, "lanes": [
                { "lane": 4, "swimmerName": "James Taylor", "team": "AQN", "seedTime": "32.90" },
                { "lane": 5, "swimmerName": "Benjamin Anderson", "team": "SCS", "seedTime": "33.15" }
            ]}
        ]
    },
    {
        "id": 17,
        "eventNumber": 17,
        "name": "Girls 9-10 100m Freestyle",
        "time": "9:32 AM",
        "heats": [
            { "heatNumber": 1, "lanes": [
                { "lane": 4, "swimmerName": "Amelia Miller", "team": "AQN", "seedTime": "1:14.00" }
            ]}
        ]
    },
    {
        "id": 18,
        "eventNumber": 18,
        "name": "Boys 9-10 100m Freestyle",
        "time": "9:34 AM",
        "heats": [
            { "heatNumber": 1, "lanes": [
                { "lane": 4, "swimmerName": "James Taylor", "team": "AQN", "seedTime": "1:12.80" }
            ]}
        ]
    },
    {
        "id": 19,
        "eventNumber": 19,
        "name": "Girls 9-10 50m Backstroke",
        "time": "9:36 AM",
        "heats": [
            { "heatNumber": 1, "lanes": [
                { "lane": 4, "swimmerName": "Emma Brown", "team": "BARR", "seedTime": "40.10" }
            ]}
        ]
    },
    {
        "id": 20,
        "eventNumber": 20,
        "name": "Boys 9-10 50m Backstroke",
        "time": "9:38 AM",
        "heats": [
            { "heatNumber": 1, "lanes": [
                { "lane": 4, "swimmerName": "Benjamin Anderson", "team": "SCS", "seedTime": "39.90" }
            ]}
        ]
    },
    {
        "id": 21,
        "eventNumber": 21,
        "name": "Girls 9-10 50m Breaststroke",
        "time": "9:40 AM",
        "heats": [
            { "heatNumber": 1, "lanes": [
                { "lane": 4, "swimmerName": "Evelyn Wilson", "team": "SCS", "seedTime": "45.20" }
            ]}
        ]
    },
    {
        "id": 22,
        "eventNumber": 22,
        "name": "Boys 9-10 50m Breaststroke",
        "time": "9:42 AM",
        "heats": [
            { "heatNumber": 1, "lanes": [
                { "lane": 4, "swimmerName": "William Gautreaux", "team": "KLR", "seedTime": "46.10" }
            ]}
        ]
    },
    {
        "id": 23,
        "eventNumber": 23,
        "name": "Girls 9-10 50m Butterfly",
        "time": "9:44 AM",
        "heats": [
            { "heatNumber": 1, "lanes": [
                { "lane": 4, "swimmerName": "Olivia Williams", "team": "KLR", "seedTime": "38.50" }
            ]}
        ]
    },
    {
        "id": 24,
        "eventNumber": 24,
        "name": "Boys 9-10 50m Butterfly",
        "time": "9:46 AM",
        "heats": [
            { "heatNumber": 1, "lanes": [
                { "lane": 4, "swimmerName": "Lucas Hernandez", "team": "BARR", "seedTime": "39.00" }
            ]}
        ]
    },
    {
        "id": 25,
        "eventNumber": 25,
        "name": "Girls 9-10 100m IM",
        "time": "9:48 AM",
        "heats": [
            { "heatNumber": 1, "lanes": [
                { "lane": 4, "swimmerName": "Amelia Miller", "team": "AQN", "seedTime": "1:25.50" }
            ]}
        ]
    },
    {
        "id": 26,
        "eventNumber": 26,
        "name": "Boys 9-10 100m IM",
        "time": "9:50 AM",
        "heats": [
            { "heatNumber": 1, "lanes": [
                { "lane": 4, "swimmerName": "James Taylor", "team": "AQN", "seedTime": "1:24.80" }
            ]}
        ]
    },
    {
      "id": 27,
      "eventNumber": 27,
      "name": "Girls 11-12 50m Freestyle",
      "time": "9:52 AM",
      "heats": [
        { "heatNumber": 1, "lanes": [
            { "lane": 3, "swimmerName": "Madison Thomas", "team": "BARR", "seedTime": "31.90" },
            { "lane": 4, "swimmerName": "Elizabeth Jackson", "team": "AQN", "seedTime": "31.10" },
            { "lane": 5, "swimmerName": "Sofia White", "team": "SCS", "seedTime": "31.50" }
        ]}
      ]
    },
    {
      "id": 28,
      "eventNumber": 28,
      "name": "Boys 11-12 50m Freestyle",
      "time": "9:54 AM",
      "heats": [
        { "heatNumber": 1, "lanes": [
            { "lane": 4, "swimmerName": "Michael Harris", "team": "AQN", "seedTime": "30.50" },
            { "lane": 5, "swimmerName": "Alexander Clark", "team": "SCS", "seedTime": "30.99" }
        ]}
      ]
    },
    {
        "id": 29,
        "eventNumber": 29,
        "name": "Girls 11-12 100m Freestyle",
        "time": "9:56 AM",
        "heats": [
            { "heatNumber": 1, "lanes": [
                { "lane": 4, "swimmerName": "Elizabeth Jackson", "team": "AQN", "seedTime": "1:08.20" }
            ]}
        ]
    },
    {
        "id": 30,
        "eventNumber": 30,
        "name": "Boys 11-12 100m Freestyle",
        "time": "9:58 AM",
        "heats": [
            { "heatNumber": 1, "lanes": [
                { "lane": 4, "swimmerName": "Michael Harris", "team": "AQN", "seedTime": "1:06.90" }
            ]}
        ]
    },
    {
        "id": 31,
        "eventNumber": 31,
        "name": "Girls 11-12 50m Backstroke",
        "time": "10:00 AM",
        "heats": [
            { "heatNumber": 1, "lanes": [
                { "lane": 4, "swimmerName": "Sofia White", "team": "SCS", "seedTime": "36.80" }
            ]}
        ]
    },
    {
        "id": 32,
        "eventNumber": 32,
        "name": "Boys 11-12 50m Backstroke",
        "time": "10:02 AM",
        "heats": [
            { "heatNumber": 1, "lanes": [
                { "lane": 4, "swimmerName": "Alexander Clark", "team": "SCS", "seedTime": "35.70" }
            ]}
        ]
    },
    {
        "id": 33,
        "eventNumber": 33,
        "name": "Girls 11-12 100m Backstroke",
        "time": "10:04 AM",
        "heats": [
            { "heatNumber": 1, "lanes": [
                { "lane": 4, "swimmerName": "Madison Thomas", "team": "BARR", "seedTime": "1:18.50" }
            ]}
        ]
    },
    {
        "id": 34,
        "eventNumber": 34,
        "name": "Boys 11-12 100m Backstroke",
        "time": "10:06 AM",
        "heats": [
            { "heatNumber": 1, "lanes": [
                { "lane": 4, "swimmerName": "Jacob Landry", "team": "KLR", "seedTime": "1:17.90" }
            ]}
        ]
    },
    {
        "id": 35,
        "eventNumber": 35,
        "name": "Girls 11-12 50m Breaststroke",
        "time": "10:08 AM",
        "heats": [
            { "heatNumber": 1, "lanes": [
                { "lane": 4, "swimmerName": "Avery Richard", "team": "AQN", "seedTime": "41.20" }
            ]}
        ]
    },
    {
        "id": 36,
        "eventNumber": 36,
        "name": "Boys 11-12 50m Breaststroke",
        "time": "10:10 AM",
        "heats": [
            { "heatNumber": 1, "lanes": [
                { "lane": 4, "swimmerName": "Elijah Romero", "team": "SCS", "seedTime": "40.50" }
            ]}
        ]
    },
    {
        "id": 37,
        "eventNumber": 37,
        "name": "Girls 11-12 100m Breaststroke",
        "time": "10:12 AM",
        "heats": [
            { "heatNumber": 1, "lanes": [
                { "lane": 4, "swimmerName": "Avery Richard", "team": "AQN", "seedTime": "1:30.10" }
            ]}
        ]
    },
    {
        "id": 38,
        "eventNumber": 38,
        "name": "Boys 11-12 100m Breaststroke",
        "time": "10:14 AM",
        "heats": [
            { "heatNumber": 1, "lanes": [
                { "lane": 4, "swimmerName": "Elijah Romero", "team": "SCS", "seedTime": "1:28.90" }
            ]}
        ]
    },
    {
        "id": 39,
        "eventNumber": 39,
        "name": "Girls 11-12 50m Butterfly",
        "time": "10:16 AM",
        "heats": [
            { "heatNumber": 1, "lanes": [
                { "lane": 4, "swimmerName": "Elizabeth Jackson", "team": "AQN", "seedTime": "34.50" }
            ]}
        ]
    },
    {
        "id": 40,
        "eventNumber": 40,
        "name": "Boys 11-12 50m Butterfly",
        "time": "10:18 AM",
        "heats": [
            { "heatNumber": 1, "lanes": [
                { "lane": 4, "swimmerName": "Michael Harris", "team": "AQN", "seedTime": "33.80" }
            ]}
        ]
    },
    {
        "id": 41,
        "eventNumber": 41,
        "name": "Girls 11-12 100m Butterfly",
        "time": "10:20 AM",
        "heats": [
            { "heatNumber": 1, "lanes": [
                { "lane": 4, "swimmerName": "Madison Thomas", "team": "BARR", "seedTime": "1:15.80" }
            ]}
        ]
    },
    {
        "id": 42,
        "eventNumber": 42,
        "name": "Boys 11-12 100m Butterfly",
        "time": "10:22 AM",
        "heats": [
            { "heatNumber": 1, "lanes": [
                { "lane": 4, "swimmerName": "Alexander Clark", "team": "SCS", "seedTime": "1:14.50" }
            ]}
        ]
    },
    {
        "id": 43,
        "eventNumber": 43,
        "name": "Girls 11-12 200m IM",
        "time": "10:24 AM",
        "heats": [
            { "heatNumber": 1, "lanes": [
                { "lane": 4, "swimmerName": "Elizabeth Jackson", "team": "AQN", "seedTime": "2:45.10" }
            ]}
        ]
    },
    {
        "id": 44,
        "eventNumber": 44,
        "name": "Boys 11-12 200m IM",
        "time": "10:28 AM",
        "heats": [
            { "heatNumber": 1, "lanes": [
                { "lane": 4, "swimmerName": "Michael Harris", "team": "AQN", "seedTime": "2:42.80" }
            ]}
        ]
    },
    {
        "id": 45,
        "eventNumber": 45,
        "name": "Girls 13-14 50m Freestyle",
        "time": "10:32 AM",
        "heats": [
            { "heatNumber": 1, "lanes": [
                { "lane": 4, "swimmerName": "Chloe Lewis", "team": "KLR", "seedTime": "29.80" },
                { "lane": 5, "swimmerName": "Grace Walker", "team": "BARR", "seedTime": "30.10" }
            ]}
        ]
    },
    {
        "id": 46,
        "eventNumber": 46,
        "name": "Boys 13-14 50m Freestyle",
        "time": "10:34 AM",
        "heats": [
            { "heatNumber": 1, "lanes": [
                { "lane": 3, "swimmerName": "Daniel Hall", "team": "SCS", "seedTime": "28.50" },
                { "lane": 4, "swimmerName": "Matthew Allen", "team": "AQN", "seedTime": "28.10" },
                { "lane": 5, "swimmerName": "Joseph Young", "team": "BARR", "seedTime": "28.40" }
            ]}
        ]
    },
    {
        "id": 47,
        "eventNumber": 47,
        "name": "Girls 13-14 100m Freestyle",
        "time": "10:36 AM",
        "heats": [
            { "heatNumber": 1, "lanes": [
                { "lane": 4, "swimmerName": "Chloe Lewis", "team": "KLR", "seedTime": "1:04.50" }
            ]}
        ]
    },
    {
        "id": 48,
        "eventNumber": 48,
        "name": "Boys 13-14 100m Freestyle",
        "time": "10:38 AM",
        "heats": [
            { "heatNumber": 1, "lanes": [
                { "lane": 4, "swimmerName": "Matthew Allen", "team": "AQN", "seedTime": "1:01.20" }
            ]}
        ]
    },
    {
        "id": 49,
        "eventNumber": 49,
        "name": "Girls 13-14 200m Freestyle",
        "time": "10:40 AM",
        "heats": [
            { "heatNumber": 1, "lanes": [
                { "lane": 4, "swimmerName": "Grace Walker", "team": "BARR", "seedTime": "2:20.10" }
            ]}
        ]
    },
    {
        "id": 50,
        "eventNumber": 50,
        "name": "Boys 13-14 200m Freestyle",
        "time": "10:43 AM",
        "heats": [
            { "heatNumber": 1, "lanes": [
                { "lane": 4, "swimmerName": "Matthew Allen", "team": "AQN", "seedTime": "2:12.80" }
            ]}
        ]
    },
    {
        "id": 51,
        "eventNumber": 51,
        "name": "Girls 13-14 100m Backstroke",
        "time": "10:46 AM",
        "heats": [
            { "heatNumber": 1, "lanes": [
                { "lane": 4, "swimmerName": "Zoe Patel", "team": "SCS", "seedTime": "1:12.30" }
            ]}
        ]
    },
    {
        "id": 52,
        "eventNumber": 52,
        "name": "Boys 13-14 100m Backstroke",
        "time": "10:48 AM",
        "heats": [
            { "heatNumber": 1, "lanes": [
                { "lane": 4, "swimmerName": "Daniel Hall", "team": "SCS", "seedTime": "1:08.90" }
            ]}
        ]
    },
    {
        "id": 53,
        "eventNumber": 53,
        "name": "Girls 13-14 100m Breaststroke",
        "time": "10:50 AM",
        "heats": [
            { "heatNumber": 1, "lanes": [
                { "lane": 4, "swimmerName": "Hannah Rivera", "team": "KLR", "seedTime": "1:22.50" }
            ]}
        ]
    },
    {
        "id": 54,
        "eventNumber": 54,
        "name": "Boys 13-14 100m Breaststroke",
        "time": "10:52 AM",
        "heats": [
            { "heatNumber": 1, "lanes": [
                { "lane": 4, "swimmerName": "Joseph Young", "team": "BARR", "seedTime": "1:19.80" }
            ]}
        ]
    },
    {
        "id": 55,
        "eventNumber": 55,
        "name": "Girls 13-14 100m Butterfly",
        "time": "10:54 AM",
        "heats": [
            { "heatNumber": 1, "lanes": [
                { "lane": 4, "swimmerName": "Chloe Lewis", "team": "KLR", "seedTime": "1:10.50" }
            ]}
        ]
    },
    {
        "id": 56,
        "eventNumber": 56,
        "name": "Boys 13-14 100m Butterfly",
        "time": "10:56 AM",
        "heats": [
            { "heatNumber": 1, "lanes": [
                { "lane": 4, "swimmerName": "Matthew Allen", "team": "AQN", "seedTime": "1:04.20" }
            ]}
        ]
    },
    {
        "id": 57,
        "eventNumber": 57,
        "name": "Girls 13-14 200m IM",
        "time": "10:58 AM",
        "heats": [
            { "heatNumber": 1, "lanes": [
                { "lane": 4, "swimmerName": "Chloe Lewis", "team": "KLR", "seedTime": "2:35.60" }
            ]}
        ]
    },
    {
        "id": 58,
        "eventNumber": 58,
        "name": "Boys 13-14 200m IM",
        "time": "11:01 AM",
        "heats": [
            { "heatNumber": 1, "lanes": [
                { "lane": 4, "swimmerName": "Daniel Hall", "team": "SCS", "seedTime": "2:28.90" }
            ]}
        ]
    },
    {
      "id": 59,
      "eventNumber": 59,
      "name": "Girls 15-17 50m Freestyle",
      "time": "11:04 AM",
      "heats": [
        { "heatNumber": 1, "lanes": [
            { "lane": 4, "swimmerName": "Natalie King", "team": "KLR", "seedTime": "28.50" },
            { "lane": 5, "swimmerName": "Lily Wright", "team": "SCS", "seedTime": "28.90" }
        ]}
      ]
    },
    {
      "id": 60,
      "eventNumber": 60,
      "name": "Boys 15-17 50m Freestyle",
      "time": "11:06 AM",
      "heats": [
        { "heatNumber": 1, "lanes": [
            { "lane": 4, "swimmerName": "David Scott", "team": "AQN", "seedTime": "26.10" },
            { "lane": 5, "swimmerName": "Christopher Green", "team": "BARR", "seedTime": "26.40" }
        ]}
      ]
    },
    {
      "id": 61,
      "eventNumber": 61,
      "name": "Girls 15-17 100m Freestyle",
      "time": "11:08 AM",
      "heats": [
        { "heatNumber": 1, "lanes": [
            { "lane": 4, "swimmerName": "Natalie King", "team": "KLR", "seedTime": "1:02.30" }
        ]}
      ]
    },
    {
      "id": 62,
      "eventNumber": 62,
      "name": "Boys 15-17 100m Freestyle",
      "time": "11:10 AM",
      "heats": [
        { "heatNumber": 1, "lanes": [
            { "lane": 4, "swimmerName": "David Scott", "team": "AQN", "seedTime": "57.80" }
        ]}
      ]
    },
    {
      "id": 63,
      "eventNumber": 63,
      "name": "Girls 15-17 200m Freestyle",
      "time": "11:12 AM",
      "heats": [
        { "heatNumber": 1, "lanes": [
            { "lane": 4, "swimmerName": "Lily Wright", "team": "SCS", "seedTime": "2:16.50" }
        ]}
      ]
    },
    {
      "id": 64,
      "eventNumber": 64,
      "name": "Boys 15-17 200m Freestyle",
      "time": "11:15 AM",
      "heats": [
        { "heatNumber": 1, "lanes": [
            { "lane": 4, "swimmerName": "David Scott", "team": "AQN", "seedTime": "2:05.10" }
        ]}
      ]
    },
    {
      "id": 65,
      "eventNumber": 65,
      "name": "Girls 15-17 100m Backstroke",
      "time": "11:18 AM",
      "heats": [
        { "heatNumber": 1, "lanes": [
            { "lane": 4, "swimmerName": "Sarah Hill", "team": "BARR", "seedTime": "1:09.90" }
        ]}
      ]
    },
    {
      "id": 66,
      "eventNumber": 66,
      "name": "Boys 15-17 100m Backstroke",
      "time": "11:20 AM",
      "heats": [
        { "heatNumber": 1, "lanes": [
            { "lane": 4, "swimmerName": "Kevin Adams", "team": "KLR", "seedTime": "1:05.20" }
        ]}
      ]
    },
    {
      "id": 67,
      "eventNumber": 67,
      "name": "Girls 15-17 100m Breaststroke",
      "time": "11:22 AM",
      "heats": [
        { "heatNumber": 1, "lanes": [
            { "lane": 4, "swimmerName": "Jessica Baker", "team": "SCS", "seedTime": "1:20.10" }
        ]}
      ]
    },
    {
      "id": 68,
      "eventNumber": 68,
      "name": "Boys 15-17 100m Breaststroke",
      "time": "11:24 AM",
      "heats": [
        { "heatNumber": 1, "lanes": [
            { "lane": 4, "swimmerName": "Christopher Green", "team": "BARR", "seedTime": "1:15.80" }
        ]}
      ]
    },
    {
      "id": 69,
      "eventNumber": 69,
      "name": "Girls 15-17 100m Butterfly",
      "time": "11:26 AM",
      "heats": [
        { "heatNumber": 1, "lanes": [
            { "lane": 4, "swimmerName": "Natalie King", "team": "KLR", "seedTime": "1:08.50" }
        ]}
      ]
    },
    {
      "id": 70,
      "eventNumber": 70,
      "name": "Boys 15-17 100m Butterfly",
      "time": "11:28 AM",
      "heats": [
        { "heatNumber": 1, "lanes": [
            { "lane": 4, "swimmerName": "Paul Nelson", "team": "AQN", "seedTime": "1:02.30" }
        ]}
      ]
    },
    {
      "id": 71,
      "eventNumber": 71,
      "name": "Girls 15-17 200m IM",
      "time": "11:30 AM",
      "heats": [
        { "heatNumber": 1, "lanes": [
            { "lane": 4, "swimmerName": "Lily Wright", "team": "SCS", "seedTime": "2:30.40" }
        ]}
      ]
    },
    {
      "id": 72,
      "eventNumber": 72,
      "name": "Boys 15-17 200m IM",
      "time": "11:33 AM",
      "heats": [
        { "heatNumber": 1, "lanes": [
            { "lane": 4, "swimmerName": "David Scott", "team": "AQN", "seedTime": "2:20.10" }
        ]}
      ]
    }
  ]
}
